README.md
setup.py
cabbage/__init__.py
cabbage/core/__init__.py
cabbage/core/bcore.py
cabbage/core/dcore.py
cabbage/io/__init__.py
cabbage/io/reader.py
cabbage/io/saver.py
cabbage/model/__init__.py
cabbage/model/data.py
cabbagego.egg-info/PKG-INFO
cabbagego.egg-info/SOURCES.txt
cabbagego.egg-info/dependency_links.txt
cabbagego.egg-info/requires.txt
cabbagego.egg-info/top_level.txt